{"id":99,"name":"الزلزلة","transliteration":"Az-Zalzalah","translation":"The Earthquake","type":"medinan","total_verses":8,"verses":[{"id":1,"text":"إِذَا زُلۡزِلَتِ ٱلۡأَرۡضُ زِلۡزَالَهَا","translation":"When the earth is shaken with its [final] earthquake","transliteration":"Itha zulzilati alardu zilzalaha"},{"id":2,"text":"وَأَخۡرَجَتِ ٱلۡأَرۡضُ أَثۡقَالَهَا","translation":"And the earth discharges its burdens","transliteration":"Waakhrajati alardu athqalaha"},{"id":3,"text":"وَقَالَ ٱلۡإِنسَٰنُ مَا لَهَا","translation":"And man says, \"What is [wrong] with it","transliteration":"Waqala alinsanu ma laha"},{"id":4,"text":"يَوۡمَئِذٖ تُحَدِّثُ أَخۡبَارَهَا","translation":"That Day, it will report its news","transliteration":"Yawmaithin tuhaddithu akhbaraha"},{"id":5,"text":"بِأَنَّ رَبَّكَ أَوۡحَىٰ لَهَا","translation":"Because your Lord has commanded it","transliteration":"Bianna rabbaka awha laha"},{"id":6,"text":"يَوۡمَئِذٖ يَصۡدُرُ ٱلنَّاسُ أَشۡتَاتٗا لِّيُرَوۡاْ أَعۡمَٰلَهُمۡ","translation":"That Day, the people will depart separated [into categories] to be shown [the result of] their deeds","transliteration":"Yawmaithin yasduru alnnasu ashtatan liyuraw aAAmalahum"},{"id":7,"text":"فَمَن يَعۡمَلۡ مِثۡقَالَ ذَرَّةٍ خَيۡرٗا يَرَهُۥ","translation":"So whoever does an atom's weight of good will see it","transliteration":"Faman yaAAmal mithqala tharratin khayran yarahu"},{"id":8,"text":"وَمَن يَعۡمَلۡ مِثۡقَالَ ذَرَّةٖ شَرّٗا يَرَهُۥ","translation":"And whoever does an atom's weight of evil will see it","transliteration":"Waman yaAAmal mithqala tharratin sharran yarahu"}]}
