{"id":70,"name":"المعارج","transliteration":"Al-Ma'arij","translation":"উন্নয়নের সোপান","type":"meccan","total_verses":44,"verses":[{"id":1,"text":"سَأَلَ سَآئِلُۢ بِعَذَابٖ وَاقِعٖ","translation":"একব্যক্তি চাইল, সেই আযাব সংঘটিত হোক যা অবধারিত","transliteration":"Saala sailun biAAathabin waqiAAin"},{"id":2,"text":"لِّلۡكَٰفِرِينَ لَيۡسَ لَهُۥ دَافِعٞ","translation":"কাফেরদের জন্যে, যার প্রতিরোধকারী কেউ নেই।","transliteration":"Lilkafireena laysa lahu dafiAAun"},{"id":3,"text":"مِّنَ ٱللَّهِ ذِي ٱلۡمَعَارِجِ","translation":"তা আসবে আল্লাহ তা’আলার পক্ষ থেকে, যিনি সমুন্নত মর্তবার অধিকারী।","transliteration":"Mina Allahi thee almaAAariji"},{"id":4,"text":"تَعۡرُجُ ٱلۡمَلَـٰٓئِكَةُ وَٱلرُّوحُ إِلَيۡهِ فِي يَوۡمٖ كَانَ مِقۡدَارُهُۥ خَمۡسِينَ أَلۡفَ سَنَةٖ","translation":"ফেরেশতাগণ এবং রূহ আল্লাহ তা’আলার দিকে উর্ধ্বগামী হয় এমন একদিনে, যার পরিমাণ পঞ্চাশ হাজার বছর।","transliteration":"TaAAruju almalaikatu waalrroohu ilayhi fee yawmin kana miqdaruhu khamseena alfa sanatin"},{"id":5,"text":"فَٱصۡبِرۡ صَبۡرٗا جَمِيلًا","translation":"অতএব, আপনি উত্তম সবর করুন।","transliteration":"Faisbir sabran jameelan"},{"id":6,"text":"إِنَّهُمۡ يَرَوۡنَهُۥ بَعِيدٗا","translation":"তারা এই আযাবকে সুদূরপরাহত মনে করে","transliteration":"Innahum yarawnahu baAAeedan"},{"id":7,"text":"وَنَرَىٰهُ قَرِيبٗا","translation":"আর আমি একে আসন্ন দেখছি।","transliteration":"Wanarahu qareeban"},{"id":8,"text":"يَوۡمَ تَكُونُ ٱلسَّمَآءُ كَٱلۡمُهۡلِ","translation":"সেদিন আকাশ হবে গলিত তামার মত।","transliteration":"Yawma takoonu alssamao kaalmuhli"},{"id":9,"text":"وَتَكُونُ ٱلۡجِبَالُ كَٱلۡعِهۡنِ","translation":"এবং পর্বতসমূহ হবে রঙ্গীন পশমের মত","transliteration":"Watakoonu aljibalu kaalAAihni"},{"id":10,"text":"وَلَا يَسۡـَٔلُ حَمِيمٌ حَمِيمٗا","translation":"বন্ধু বন্ধুর খবর নিবে না।","transliteration":"Wala yasalu hameemun hameeman"},{"id":11,"text":"يُبَصَّرُونَهُمۡۚ يَوَدُّ ٱلۡمُجۡرِمُ لَوۡ يَفۡتَدِي مِنۡ عَذَابِ يَوۡمِئِذِۭ بِبَنِيهِ","translation":"যদিও একে অপরকে দেখতে পাবে। সেদিন গোনাহগার ব্যক্তি পনস্বরূপ দিতে চাইবে তার সন্তান-সন্ততিকে","transliteration":"Yubassaroonahum yawaddu almujrimu law yaftadee min AAathabi yawmiithin bibaneehi"},{"id":12,"text":"وَصَٰحِبَتِهِۦ وَأَخِيهِ","translation":"তার স্ত্রীকে, তার ভ্রাতাকে","transliteration":"Wasahibatihi waakheehi"},{"id":13,"text":"وَفَصِيلَتِهِ ٱلَّتِي تُـٔۡوِيهِ","translation":"তার গোষ্ঠীকে, যারা তাকে আশ্রয় দিত।","transliteration":"Wafaseelatihi allatee tuweehi"},{"id":14,"text":"وَمَن فِي ٱلۡأَرۡضِ جَمِيعٗا ثُمَّ يُنجِيهِ","translation":"এবং পৃথিবীর সবকিছুকে, অতঃপর নিজেকে রক্ষা করতে চাইবে।","transliteration":"Waman fee alardi jameeAAan thumma yunjeehi"},{"id":15,"text":"كَلَّآۖ إِنَّهَا لَظَىٰ","translation":"কখনই নয়। নিশ্চয় এটা লেলিহান অগ্নি।","transliteration":"Kalla innaha latha"},{"id":16,"text":"نَزَّاعَةٗ لِّلشَّوَىٰ","translation":"যা চামড়া তুলে দিবে।","transliteration":"NazzaAAatan lilshshawa"},{"id":17,"text":"تَدۡعُواْ مَنۡ أَدۡبَرَ وَتَوَلَّىٰ","translation":"সে সেই ব্যক্তিকে ডাকবে যে সত্যের প্রতি পৃষ্ঠপ্রদর্শন করেছিল ও বিমুখ হয়েছিল।","transliteration":"TadAAoo man adbara watawalla"},{"id":18,"text":"وَجَمَعَ فَأَوۡعَىٰٓ","translation":"সম্পদ পুঞ্জীভূত করেছিল, অতঃপর আগলিয়ে রেখেছিল।","transliteration":"WajamaAAa faawAAa"},{"id":19,"text":"۞إِنَّ ٱلۡإِنسَٰنَ خُلِقَ هَلُوعًا","translation":"মানুষ তো সৃজিত হয়েছে ভীরুরূপে।","transliteration":"Inna alinsana khuliqa halooAAan"},{"id":20,"text":"إِذَا مَسَّهُ ٱلشَّرُّ جَزُوعٗا","translation":"যখন তাকে অনিষ্ট স্পর্শ করে, তখন সে হা-হুতাশ করে।","transliteration":"Itha massahu alshsharru jazooAAan"},{"id":21,"text":"وَإِذَا مَسَّهُ ٱلۡخَيۡرُ مَنُوعًا","translation":"আর যখন কল্যাণপ্রাপ্ত হয়, তখন কৃপণ হয়ে যায়।","transliteration":"Waitha massahu alkhayru manooAAan"},{"id":22,"text":"إِلَّا ٱلۡمُصَلِّينَ","translation":"তবে তারা স্বতন্ত্র, যারা নামায আদায় কারী।","transliteration":"Illa almusalleena"},{"id":23,"text":"ٱلَّذِينَ هُمۡ عَلَىٰ صَلَاتِهِمۡ دَآئِمُونَ","translation":"যারা তাদের নামাযে সার্বক্ষণিক কায়েম থাকে।","transliteration":"Allatheena hum AAala salatihim daimoona"},{"id":24,"text":"وَٱلَّذِينَ فِيٓ أَمۡوَٰلِهِمۡ حَقّٞ مَّعۡلُومٞ","translation":"এবং যাদের ধন-সম্পদে নির্ধারিত হক আছে","transliteration":"Waallatheena fee amwalihim haqqun maAAloomun"},{"id":25,"text":"لِّلسَّآئِلِ وَٱلۡمَحۡرُومِ","translation":"যাঞ্ছাকারী ও বঞ্চিতের","transliteration":"Lilssaili waalmahroomi"},{"id":26,"text":"وَٱلَّذِينَ يُصَدِّقُونَ بِيَوۡمِ ٱلدِّينِ","translation":"এবং যারা প্রতিফল দিবসকে সত্য বলে বিশ্বাস করে।","transliteration":"Waallatheena yusaddiqoona biyawmi alddeeni"},{"id":27,"text":"وَٱلَّذِينَ هُم مِّنۡ عَذَابِ رَبِّهِم مُّشۡفِقُونَ","translation":"এবং যারা তাদের পালনকর্তার শাস্তির সম্পর্কে ভীত-কম্পিত।","transliteration":"Waallatheena hum min AAathabi rabbihim mushfiqoona"},{"id":28,"text":"إِنَّ عَذَابَ رَبِّهِمۡ غَيۡرُ مَأۡمُونٖ","translation":"নিশ্চয় তাদের পালনকর্তার শাস্তি থেকে নিঃশঙ্কা থাকা যায় না।","transliteration":"Inna AAathaba rabbihim ghayru mamoonin"},{"id":29,"text":"وَٱلَّذِينَ هُمۡ لِفُرُوجِهِمۡ حَٰفِظُونَ","translation":"এবং যারা তাদের যৌন-অঙ্গকে সংযত রাখে","transliteration":"Waallatheena hum lifuroojihim hafithoona"},{"id":30,"text":"إِلَّا عَلَىٰٓ أَزۡوَٰجِهِمۡ أَوۡ مَا مَلَكَتۡ أَيۡمَٰنُهُمۡ فَإِنَّهُمۡ غَيۡرُ مَلُومِينَ","translation":"কিন্তু তাদের স্ত্রী অথবা মালিকানাভূক্ত দাসীদের বেলায় তিরস্কৃত হবে না।","transliteration":"Illa AAala azwajihim aw ma malakat aymanuhum fainnahum ghayru maloomeena"},{"id":31,"text":"فَمَنِ ٱبۡتَغَىٰ وَرَآءَ ذَٰلِكَ فَأُوْلَـٰٓئِكَ هُمُ ٱلۡعَادُونَ","translation":"অতএব, যারা এদের ছাড়া অন্যকে কামনা করে, তারাই সীমালংঘনকারী।","transliteration":"Famani ibtagha waraa thalika faolaika humu alAAadoona"},{"id":32,"text":"وَٱلَّذِينَ هُمۡ لِأَمَٰنَٰتِهِمۡ وَعَهۡدِهِمۡ رَٰعُونَ","translation":"এবং যারা তাদের আমানত ও অঙ্গীকার রক্ষা করে","transliteration":"Waallatheena hum liamanatihim waAAahdihim raAAoona"},{"id":33,"text":"وَٱلَّذِينَ هُم بِشَهَٰدَٰتِهِمۡ قَآئِمُونَ","translation":"এবং যারা তাদের সাক্ষ্যদানে সরল-নিষ্ঠাবান","transliteration":"Waallatheena hum bishahadatihim qaimoona"},{"id":34,"text":"وَٱلَّذِينَ هُمۡ عَلَىٰ صَلَاتِهِمۡ يُحَافِظُونَ","translation":"এবং যারা তাদের নামাযে যত্নবান","transliteration":"Waallatheena hum AAala salatihim yuhafithoona"},{"id":35,"text":"أُوْلَـٰٓئِكَ فِي جَنَّـٰتٖ مُّكۡرَمُونَ","translation":"তারাই জান্নাতে সম্মানিত হবে।","transliteration":"Olaika fee jannatin mukramoona"},{"id":36,"text":"فَمَالِ ٱلَّذِينَ كَفَرُواْ قِبَلَكَ مُهۡطِعِينَ","translation":"অতএব, কাফেরদের কি হল যে, তারা আপনার দিকে উর্ধ্বশ্বাসে ছুটে আসছে।","transliteration":"Famali allatheena kafaroo qibalaka muhtiAAeena"},{"id":37,"text":"عَنِ ٱلۡيَمِينِ وَعَنِ ٱلشِّمَالِ عِزِينَ","translation":"ডান ও বামদিক থেকে দলে দলে।","transliteration":"AAani alyameeni waAAani alshshimali AAizeena"},{"id":38,"text":"أَيَطۡمَعُ كُلُّ ٱمۡرِيٕٖ مِّنۡهُمۡ أَن يُدۡخَلَ جَنَّةَ نَعِيمٖ","translation":"তাদের প্রত্যেকেই কি আশা করে যে, তাকে নেয়ামতের জান্নাতে দাখিল করা হবে","transliteration":"AyatmaAAu kullu imriin minhum an yudkhala jannata naAAeemin"},{"id":39,"text":"كَلَّآۖ إِنَّا خَلَقۡنَٰهُم مِّمَّا يَعۡلَمُونَ","translation":"কখনই নয়, আমি তাদেরকে এমন বস্তু দ্বারা সৃষ্টি করেছি, যা তারা জানে।","transliteration":"Kalla inna khalaqnahum mimma yaAAlamoona"},{"id":40,"text":"فَلَآ أُقۡسِمُ بِرَبِّ ٱلۡمَشَٰرِقِ وَٱلۡمَغَٰرِبِ إِنَّا لَقَٰدِرُونَ","translation":"আমি শপথ করছি উদয়াচল ও অস্তাচলসমূহের পালনকর্তার, নিশ্চয়ই আমি সক্ষম","transliteration":"Fala oqsimu birabbi almashariqi waalmagharibi inna laqadiroona"},{"id":41,"text":"عَلَىٰٓ أَن نُّبَدِّلَ خَيۡرٗا مِّنۡهُمۡ وَمَا نَحۡنُ بِمَسۡبُوقِينَ","translation":"তাদের পরিবর্তে উৎকৃষ্টতর মানুষ সৃষ্টি করতে এবং এটা আমার সাধ্যের অতীত নয়।","transliteration":"AAala an nubaddila khayran minhum wama nahnu bimasbooqeena"},{"id":42,"text":"فَذَرۡهُمۡ يَخُوضُواْ وَيَلۡعَبُواْ حَتَّىٰ يُلَٰقُواْ يَوۡمَهُمُ ٱلَّذِي يُوعَدُونَ","translation":"অতএব, আপনি তাদেরকে ছেড়ে দিন, তারা বাকবিতন্ডা ও ক্রীড়া-কৌতুক করুক সেই দিবসের সম্মুখীন হওয়া পর্যন্ত, যে দিবসের ওয়াদা তাদের সাথে করা হচ্ছে।","transliteration":"Fatharhum yakhoodoo wayalAAaboo hatta yulaqoo yawmahumu allathee yooAAadoona"},{"id":43,"text":"يَوۡمَ يَخۡرُجُونَ مِنَ ٱلۡأَجۡدَاثِ سِرَاعٗا كَأَنَّهُمۡ إِلَىٰ نُصُبٖ يُوفِضُونَ","translation":"সে দিন তারা কবর থেকে দ্রুতবেগে বের হবে, যেন তারা কোন এক লক্ষ্যস্থলের দিকে ছুটে যাচ্ছে।","transliteration":"Yawma yakhrujoona mina alajdathi siraAAan kaannahum ila nusubin yoofidoona"},{"id":44,"text":"خَٰشِعَةً أَبۡصَٰرُهُمۡ تَرۡهَقُهُمۡ ذِلَّةٞۚ ذَٰلِكَ ٱلۡيَوۡمُ ٱلَّذِي كَانُواْ يُوعَدُونَ","translation":"তাদের দৃষ্টি থাকবে অবনমিত; তারা হবে হীনতাগ্রস্ত। এটাই সেইদিন, যার ওয়াদা তাদেরকে দেয়া হত।","transliteration":"KhashiAAatan absaruhum tarhaquhum thillatun thalika alyawmu allathee kanoo yooAAadoona"}]}
