{
  "number": 108,
  "name": "سورة الكوثر",
  "transliteration_en": "Al-Kawthar",
  "translation_en": "Abundance",
  "total_verses": 3,
  "revelation_type": "Meccan",
  "verses": [
    {
      "number": 1,
      "text": "بِسْمِ ٱللَّهِ ٱلرَّحْمَٰنِ ٱلرَّحِيمِ إِنَّآ أَعْطَيْنَٰكَ ٱلْكَوْثَرَ",
      "translation_en": "Indeed, We have granted you, [O Muhammad], al-Kawthar.",
      "translation_id": "Sesungguhnya Kami telah memberikan kepadamu nikmat yang banyak."
    },
    {
      "number": 2,
      "text": "فَصَلِّ لِرَبِّكَ وَٱنْحَرْ",
      "translation_en": "So pray to your Lord and sacrifice [to Him alone].",
      "translation_id": "Maka dirikanlah shalat karena Tuhanmu; dan berkorbanlah."
    },
    {
      "number": 3,
      "text": "إِنَّ شَانِئَكَ هُوَ ٱلْأَبْتَرُ",
      "translation_en": "Indeed, your enemy is the one cut off.",
      "translation_id": "Sesungguhnya orang-orang yang membenci kamu dialah yang terputus."
    }
  ]
}