{"id":1544,"number":71,"text":"وَٱمۡرَأَتُهُۥ قَآئِمَةٞ فَضَحِكَتۡ فَبَشَّرۡنَٰهَا بِإِسۡحَٰقَ وَمِن وَرَآءِ إِسۡحَٰقَ يَعۡقُوبَ","translation":{"en":"And his Wife was standing, and she smiled. Then We gave her good tidings of Isaac and after Isaac, Jacob","id":"Dan istrinya berdiri lalu dia tersenyum. Maka Kami sampaikan kepadanya kabar gembira tentang (kelahiran) Ishak dan setelah Ishak (akan lahir) Yakub"},"chapter":{"id":11,"name":"هود","transliteration":"Hud","translation":{"en":"Hud","id":"Hud"},"type":"meccan"}}
