{"id":1670,"number":74,"text":"قَالُواْ فَمَا جَزَـٰٓؤُهُۥٓ إِن كُنتُمۡ كَٰذِبِينَ","translations":{"bn":"তারা বললঃ যদি তোমরা মিথ্যাবাদী হও, তবে যে, চুরি করেছে তার কি শাস্তি","en":"The accusers said, \"Then what would be its recompense if you should be liars","id":"Mereka berkata, \"Tetapi apa hukumannya jika kamu dusta","ru":"Они сказали: «Каким же будет возмездие ему, если вы лжете?»","tr":"Yalancı iseniz, hırsızlığın cezası nedir?\" dediler","ur":"اُنہوں نے کہا \"اچھا، اگر تمہاری بات جھوٹی نکلی تو چور کی کیا سزا ہے؟"},"chapter":{"id":12,"name":"يوسف","transliteration":"Yusuf","translations":{"bn":"নবী ইউসুফ","en":"Joseph","id":"Yusuf","ru":"Йусуф","tr":"Yûsuf","ur":"یوسف"},"type":"meccan"}}
