{"id":2370,"number":22,"text":"وَٱضۡمُمۡ يَدَكَ إِلَىٰ جَنَاحِكَ تَخۡرُجۡ بَيۡضَآءَ مِنۡ غَيۡرِ سُوٓءٍ ءَايَةً أُخۡرَىٰ","translations":{"bn":"তোমার হাত বগলে রাখ, তা বের হয়ে আসবে নির্মল উজ্জ্বল হয়ে অন্য এক নিদর্শন রূপে; কোন দোষ ছাড়াই।","en":"And draw in your hand to your side; it will come out white without disease - another sign","id":"dan kepitlah tanganmu ke ketiakmu, niscaya ia ke luar menjadi putih (bercahaya) tanpa cacat, sebagai mukjizat yang lain","ru":"Прижми свою руку к боку, и она выйдет белой (цвета молока, светящейся), без следов болезни. Вот тебе еще одно знамение","tr":"Allah: \"Onu al, korkma; biz onu yine eski durumuna çevireceğiz. Daha büyük mucizelerimizi sana göstermemiz için elini koltuğunun altına koy da, diğer bir mucize olarak, kusursuz, bembeyaz çıksın\" dedi","ur":"اور ذرا اپنا ہاتھ اپنی بغل میں دبا، چمکتا ہوا نکلے گا بغیر کسی تکلیف کے یہ دوسری نشانی ہے"},"chapter":{"id":20,"name":"طه","transliteration":"Taha","translations":{"bn":"ত়া হা","en":"Ta-Ha","id":"Tha-Ha","ru":"Та Ха ","tr":"Tâhâ","ur":"طٰہٰ"},"type":"meccan"}}
