{"id":2383,"number":35,"text":"إِنَّكَ كُنتَ بِنَا بَصِيرٗا","translations":{"en":"Indeed, You are of us ever Seeing","es":"Tú bien ves que necesitamos de Ti","fr":"Et Toi, certes, Tu es Très Clairvoyant sur nous»","id":"sesungguhnya Engkau Maha Melihat (keadaan) kami","ru":"Воистину, Ты видишь нас»","sv":"Du som ser oss [som vi är med våra fel och brister]","tr":"Musa: \"Rabbim! Göğsümü genişlet, işimi kolaylaştır, dilimin düğümünü çöz ki sözümü iyi anlasınlar. Ailemden kardeşim Harun'u bana vezir yap, beni onunla destekle, onu görevimde ortak kıl ki Seni daha çok tesbih edelim ve çokça analım. Şüphesiz Sen bizi görmektesin\" dedi","ur":"تو ہمیشہ ہمارے حال پر نگران رہا ہے","zh":"你确是明察我们的。"},"transliteration":"Innaka kunta bina baseeran","chapter":{"id":20,"name":"طه","transliteration":"Taha","translations":{"en":"Ta-Ha","es":"Ta-Ha","fr":"Ta-Ha","id":"Tha-Ha","ru":"Та Ха ","sv":"Ta-Ha","tr":"Tâhâ","ur":"طٰہٰ","zh":"塔哈"},"type":"meccan"}}
