{"id":2935,"number":3,"text":"لَعَلَّكَ بَٰخِعٞ نَّفۡسَكَ أَلَّا يَكُونُواْ مُؤۡمِنِينَ","translations":{"bn":"তারা বিশ্বাস করে না বলে আপনি হয়তো মর্মব্যথায় আত্নঘাতী হবেন।","en":"Perhaps, [O Muhammad], you would kill yourself with grief that they will not be believers","id":"Boleh jadi engkau (Muhammad) akan membinasakan dirimu (dengan kesedihan), karena mereka (penduduk Mekkah) tidak beriman","ru":"Ты можешь погубить себя от скорби оттого, что они не становятся верующими","tr":"İnanmıyorlar diye nerdeyse kendini mahvedeceksin","ur":"اے محمدؐ، شاید تم اس غم میں اپنی جان کھو دو گے کہ یہ لوگ ایمان نہیں لاتے"},"chapter":{"id":26,"name":"الشعراء","transliteration":"Ash-Shu'ara","translations":{"bn":"কবি","en":"The Poets","id":"Penyair","ru":"Поэты","tr":"Şuarâ","ur":"شعراٗ"},"type":"meccan"}}
