{"id":3018,"number":86,"text":"وَٱغۡفِرۡ لِأَبِيٓ إِنَّهُۥ كَانَ مِنَ ٱلضَّآلِّينَ","translations":{"bn":"এবং আমার পিতাকে ক্ষমা কর। সে তো পথভ্রষ্টদের অন্যতম।","en":"And forgive my father. Indeed, he has been of those astray","id":"dan ampunilah ayahku, sesungguhnya dia termasuk orang yang sesat","ru":"Прости моего отца, ибо он был одним из заблудших","tr":"Sonrakilerin beni güzel şekilde anmalarını sağla. Beni nimet cennetine varis olanlardan kıl. Babamı da bağışla, o şüphesiz sapıklardandır. İnsanların diriltileceği gün, Allah'a temiz bir kalble gelenden başka kimseye malın ve oğulların fayda vermeyeceği gün, beni rezil etme\" demişti","ur":"اور میرے باپ کو معاف کر دے کہ بے شک وہ گمراہ لوگوں میں سے ہے"},"chapter":{"id":26,"name":"الشعراء","transliteration":"Ash-Shu'ara","translations":{"bn":"কবি","en":"The Poets","id":"Penyair","ru":"Поэты","tr":"Şuarâ","ur":"شعراٗ"},"type":"meccan"}}
