{"id":3022,"number":90,"text":"وَأُزۡلِفَتِ ٱلۡجَنَّةُ لِلۡمُتَّقِينَ","translations":{"bn":"জান্নাত আল্লাহভীরুদের নিকটবর্তী করা হবে।","en":"And Paradise will be brought near [that Day] to the righteous","id":"dan surga didekatkan kepada orang-orang yang bertakwa","ru":"Рай будет приближен к богобоязненным","tr":"O gün cennet Allah'a karşı gelmekten sakınanlara yaklaştırılır. Cehennem de azgınlara gösterilir","ur":"(اس روز) جنت پرہیزگاروں کے قریب لے آئی جائے گی"},"chapter":{"id":26,"name":"الشعراء","transliteration":"Ash-Shu'ara","translations":{"bn":"কবি","en":"The Poets","id":"Penyair","ru":"Поэты","tr":"Şuarâ","ur":"شعراٗ"},"type":"meccan"}}
