{"id":3070,"number":138,"text":"وَمَا نَحۡنُ بِمُعَذَّبِينَ","translations":{"en":"And we are not to be punished","es":"y seguramente no seremos castigados","fr":"Nous ne serons nullement châtiés»","id":"dan kami (sama sekali) tidak akan di azab","ru":"и мы не будем наказаны»","sv":"och vi kommer inte att straffas [för detta]","tr":"Bu durumumuz öncekilerin geleneğidir. Biz azaba uğratılacak da değiliz\" dediler","ur":"اور ہم عذاب میں مُبتلا ہونے والے نہیں ہیں","zh":"我们绝不会受惩罚的。”"},"transliteration":"Wama nahnu bimuAAaththabeena","chapter":{"id":26,"name":"الشعراء","transliteration":"Ash-Shu'ara","translations":{"en":"The Poets","es":"Los Poetas","fr":"Les poètes","id":"Penyair","ru":"Поэты","sv":"Poeterna","tr":"Şuarâ","ur":"شعراٗ","zh":"众诗人"},"type":"meccan"}}
