{"id":3464,"number":55,"text":"وَيَوۡمَ تَقُومُ ٱلسَّاعَةُ يُقۡسِمُ ٱلۡمُجۡرِمُونَ مَا لَبِثُواْ غَيۡرَ سَاعَةٖۚ كَذَٰلِكَ كَانُواْ يُؤۡفَكُونَ","translation":{"en":"And the Day the Hour appears the criminals will swear they had remained but an hour. Thus they were deluded","id":"Dan pada hari (ketika) terjadinya Kiamat, orang-orang yang berdosa bersumpah, bahwa mereka berdiam (dalam kubur) hanya sesaat (saja). Begitulah dahulu mereka dipalingkan (dari kebenaran)"},"chapter":{"id":30,"name":"الروم","transliteration":"Ar-Rum","translation":{"en":"The Romans","id":"Bangsa Romawi"},"type":"meccan"}}
