{"id":3934,"number":146,"text":"وَأَنۢبَتۡنَا عَلَيۡهِ شَجَرَةٗ مِّن يَقۡطِينٖ","translations":{"en":"And We caused to grow over him a gourd vine","es":"que ordené crecer una planta de calabaza para que lo cubriera","fr":"Et Nous fîmes pousser au-dessus de lui un plant de courge","id":"Kemudian untuk dia Kami tumbuhkan sebatang pohon dari jenis labu","ru":"Мы взрастили над ним (или возле него) тыкву","sv":"och Vi lät en kurbitsplanta växa upp över honom","tr":"Onun için, geniş yapraklı bir bitki yetiştirdik","ur":"اور اُس پر ایک بیل دار درخت اگا دیا","zh":"我使一棵瓠瓜，长起来遮着他。"},"transliteration":"Waanbatna AAalayhi shajaratan min yaqteenin","chapter":{"id":37,"name":"الصافات","transliteration":"As-Saffat","translations":{"en":"Those who set the Ranks","es":"Los Que se Ponen en Filas","fr":"Les rangés","id":"Barisan-barisan","ru":"Выстроившиеся в ряды","sv":"I Sluten Ordning","tr":"Sâffât","ur":"صف باندھنے والے","zh":"列班者"},"type":"meccan"}}
