{"id":3951,"number":163,"text":"إِلَّا مَنۡ هُوَ صَالِ ٱلۡجَحِيمِ","translations":{"bn":"শুধুমাত্র তাদের ছাড়া যারা জাহান্নামে পৌছাবে।","en":"Except he who is to [enter and] burn in the Hellfire","id":"kecuali orang-orang yang akan masuk ke neraka Jahim","ru":"кроме тех, кому суждено сгореть в Аду","tr":"Sizler ve taptığınız şeyler, cehenneme girecek kimseden başkasını Allah'a karşı azdırıcı değilsiniz","ur":"مگر صرف اُس کو جو دوزخ کی بھڑکتی ہوئی آگ میں جھلسنے والا ہو"},"chapter":{"id":37,"name":"الصافات","transliteration":"As-Saffat","translations":{"bn":"সারিবদ্ধভাবে দাঁড়ানো","en":"Those who set the Ranks","id":"Barisan-barisan","ru":"Выстроившиеся в ряды","tr":"Sâffât","ur":"صف باندھنے والے"},"type":"meccan"}}
