{"id":4222,"number":4,"text":"بَشِيرٗا وَنَذِيرٗا فَأَعۡرَضَ أَكۡثَرُهُمۡ فَهُمۡ لَا يَسۡمَعُونَ","translations":{"bn":"সুসংবাদদাতা ও সতর্ককারীরূপে, অতঃপর তাদের অধিকাংশই মুখ ফিরিয়ে নিয়েছে, তারা শুনে না।","en":"As a giver of good tidings and a warner; but most of them turn away, so they do not hear","id":"yang membawa berita gembira dan peringatan, tetapi kebanyakan mereka berpaling (darinya) serta tidak mendengarkan","ru":"Оно возвещает благую весть и предостерегает, однако большинство их отворачивается и не слышит","tr":"Bu Kitap, merhametli olan Allah katından indirilmedir; bilen bir millet için müjdeci ve uyarıcı olmak üzere Arapça okunarak, ayetleri uzun uzun açıklanmıştır. Ama insanların çoğu yüz çevirmiştir, onlar işitmezler de: \"Bizi çağırdığın şeye karşı kalblerimiz kapalıdır, kulaklarımızda ağırlık, bizimle senin aranda anlaşmamıza engel vardır; istediğini yap, biz de yapacağız\" derler","ur":"بشارت دینے والا اور ڈرا دینے والا مگر اِن لوگوں میں سے اکثر نے اس سے رو گردانی کی اور وہ سن کر نہیں دیتے"},"chapter":{"id":41,"name":"فصلت","transliteration":"Fussilat","translations":{"bn":"সুস্পষ্ট বিবরণ","en":"Explained in Detail","id":"Yang Dijelaskan","ru":"Разъяснены","tr":"Fussilet","ur":"مفصل"},"type":"meccan"}}
