{"id":4398,"number":73,"text":"لَكُمۡ فِيهَا فَٰكِهَةٞ كَثِيرَةٞ مِّنۡهَا تَأۡكُلُونَ","translations":{"bn":"তথায় তোমাদের জন্যে আছে প্রচুর ফল-মূল, তা থেকে তোমরা আহার করবে।","en":"For you therein is much fruit from which you will eat","id":"Di dalam surga itu terdapat banyak buah-buahan untukmu yang sebagiannya kamu makan","ru":"Для вас там уготованы многочисленные фрукты, которые вы будете есть","tr":"Orada sizin için bol yemiş vardır, onlardan yersiniz","ur":"تمہارے لیے یہاں بکثرت فواکہ موجود ہیں جنہیں تم کھاؤ گے"},"chapter":{"id":43,"name":"الزخرف","transliteration":"Az-Zukhruf","translations":{"bn":"সোনাদানা","en":"The Ornaments of Gold","id":"Perhiasan","ru":"Украшения","tr":"Zuhruf","ur":"سونے کی چمک"},"type":"meccan"}}
