{"id":4418,"number":4,"text":"فِيهَا يُفۡرَقُ كُلُّ أَمۡرٍ حَكِيمٍ","translations":{"bn":"এ রাতে প্রত্যেক প্রজ্ঞাপূর্ণ বিষয় স্থিরীকৃত হয়।","en":"On that night is made distinct every precise matter","id":"Pada (malam itu) dijelaskan segala urusan yang penuh hikmah","ru":"В нее решаются все мудрые дела","tr":"Katımızdan bir buyrukla, her hikmetli işe o gecede hükmedilir. Doğrusu Biz öteden beri peygamberler göndermekteyiz. Eğer kesin olarak inanırsanız bilin ki, bu senin Rabbinden, göklerin, yerin ve ikisi arasında bulunanların Rabbinden bir rahmettir. O, işitendir, bilendir","ur":"یہ وہ رات تھی جس میں ہر معاملہ کا حکیمانہ فیصلہ"},"chapter":{"id":44,"name":"الدخان","transliteration":"Ad-Dukhan","translations":{"bn":"ধোঁয়া","en":"The Smoke","id":"Kabut","ru":"Дым","tr":"Duhân","ur":"دھواں"},"type":"meccan"}}
