{"id":4576,"number":31,"text":"وَلَنَبۡلُوَنَّكُمۡ حَتَّىٰ نَعۡلَمَ ٱلۡمُجَٰهِدِينَ مِنكُمۡ وَٱلصَّـٰبِرِينَ وَنَبۡلُوَاْ أَخۡبَارَكُمۡ","translation":{"en":"And We will surely test you until We make evident those who strive among you [for the cause of Allah] and the patient, and We will test your affairs","id":"Dan sungguh, Kami benar-benar akan menguji kamu sehingga Kami mengetahui orang-orang yang benar-benar berjihad dan bersabar di antara kamu; dan akan Kami uji perihal kamu"},"chapter":{"id":47,"name":"محمد","transliteration":"Muhammad","translation":{"en":"Muhammad","id":"Muhammad"},"type":"medinan"}}
