{"id":4898,"number":52,"text":"وَكُلُّ شَيۡءٖ فَعَلُوهُ فِي ٱلزُّبُرِ","translations":{"en":"And everything they did is in written records","es":"Todo cuanto obraron se encuentra registrado en el libro de sus obras","fr":"Et tout ce qu'ils ont fait est mentionné dans les registres","id":"Dan segala sesuatu yang telah mereka perbuat tercatat dalam buku-buku catatan","ru":"Все, что они совершили, есть в книгах деяний","sv":"Alla deras handlingar omtalas i [äldre tiders] böcker med nedtecknad gudomlig visdom","tr":"İnsanların yaptıkları her şey kitablarda kayıtlıdır","ur":"جو کچھ اِنہوں نے کیا ہے وہ سب دفتروں میں درج ہے","zh":"凡他们所做的事，都记载在天经中。"},"transliteration":"Wakullu shayin faAAaloohu fee alzzuburi","chapter":{"id":54,"name":"القمر","transliteration":"Al-Qamar","translations":{"en":"The Moon","es":"La Luna","fr":"La lune","id":"Bulan","ru":"Месяц","sv":"Månen","tr":"Kamer","ur":"چاند","zh":"月亮"},"type":"meccan"}}
