{"id":5074,"number":95,"text":"إِنَّ هَٰذَا لَهُوَ حَقُّ ٱلۡيَقِينِ","translations":{"en":"Indeed, this is the true certainty","es":"esta es la Verdad sobre la que no hay duda","fr":"C'est cela la pleine certitude","id":"Sungguh, inilah keyakinan yang benar","ru":"Это и есть истина","sv":"Detta är den Sanning varom visshet råder","tr":"Doğrusu kesin gerçek budur","ur":"یہ سب کچھ قطعی حق ہے","zh":"这确是无可置疑的真理。"},"transliteration":"Inna hatha lahuwa haqqu alyaqeeni","chapter":{"id":56,"name":"الواقعة","transliteration":"Al-Waqi'ah","translations":{"en":"The Inevitable","es":"Lo Que ha de Ocurrir","fr":"L'inévitable","id":"Hari Kiamat","ru":"Событие","sv":"Det Som Måste Komma","tr":"Vâkıa","ur":"واقعہ ہونے والی قیامت","zh":"大事"},"type":"meccan"}}
