{"id":5392,"number":17,"text":"تَدۡعُواْ مَنۡ أَدۡبَرَ وَتَوَلَّىٰ","translations":{"en":"It invites he who turned his back [on truth] and went away [from obedience]","es":"y convocará a quien le dio la espalda y se apartó del Mensaje","fr":"Il appellera celui qui tournait le dos et s'en allait","id":"Yang memanggil orang yang membelakangi dan yang berpaling (dari agama)","ru":"зовущее тех, кто повернулся спиной и отвернулся","sv":"Den kallar alla dem som vände ryggen [åt budskapet] och drog sig undan","tr":"Hayır, olmaz... Orada sırtını çevirip yüzgeri edeni, malını toplayıp kimseye hakkını vermeden saklayanı çağıran, deriyi soyup kavuran, alevli ateş vardır","ur":"پکار پکار کر اپنی طرف بلائے گی ہر اُس شخص کو جس نے حق سے منہ موڑا اور پیٹھ پھیری","zh":"能召唤转身而逃避的人。"},"transliteration":"TadAAoo man adbara watawalla","chapter":{"id":70,"name":"المعارج","transliteration":"Al-Ma'arij","translations":{"en":"The Ascending Stairways","es":"Los Grados de Elevación","fr":"Les voies d'ascension","id":"Tempat yang Naik","ru":"Ступени","sv":"Vägarna Upp Till Gud","tr":"Meâric","ur":"عروج","zh":"天梯"},"type":"meccan"}}
