{"id":5435,"number":16,"text":"وَجَعَلَ ٱلۡقَمَرَ فِيهِنَّ نُورٗا وَجَعَلَ ٱلشَّمۡسَ سِرَاجٗا","translations":{"en":"And made the moon therein a [reflected] light and made the sun a burning lamp","es":"Puso en ellos la Luna para que refleje la luz y el Sol [para que la irradie] como lámpara","fr":"et y a fait de la lune une lumière et du soleil une lampe","id":"Dan di sana Dia menciptakan bulan yang bercahaya dan menjadikan matahari sebagai pelita (yang cemerlang)","ru":"сделал луну светлой, а солнце сделал светильником","sv":"och satt ibland dem månen [som lyser med lånat] ljus och solen som en sprakande fackla","tr":"Aralarında aya aydınlık vermiş ve güneşin ışık saçmasını sağlamıştır","ur":"اور اُن میں چاند کو نور اور سورج کو چراغ بنایا؟","zh":"并以月亮为光明，以太阳为明灯吗？"},"transliteration":"WajaAAala alqamara feehinna nooran wajaAAala alshshamsa sirajan","chapter":{"id":71,"name":"نوح","transliteration":"Nuh","translations":{"en":"Noah","es":"Noé","fr":"Noé","id":"Nuh","ru":"Нух","sv":"Noa","tr":"Nûh","ur":"نوح","zh":"努哈"},"type":"meccan"}}
