{"id":5578,"number":27,"text":"وَقِيلَ مَنۡۜ رَاقٖ","translations":{"bn":"এবং বলা হবে, কে ঝাড়বে","en":"And it is said, \"Who will cure [him]","id":"dan dikatakan (kepadanya), \"Siapa yang dapat menyembuhkan","ru":"будет сказано: «Кто же прочтет заклинание?»","tr":"Dikkat edin; can boğaza gelip köprücük kemiklerine dayandığı zaman: \"Çare bulan yok mudur?\" denir","ur":"اور کہا جائے گا کہ ہے کوئی جھاڑ پھونک کرنے والا"},"chapter":{"id":75,"name":"القيامة","transliteration":"Al-Qiyamah","translations":{"bn":"পুনরুত্থান","en":"The Resurrection","id":"Hari Berbangkit","ru":"Воскресение","tr":"Kıyâmet","ur":"قیامۃ"},"type":"meccan"}}
