{"id":5925,"number":16,"text":"فَعَّالٞ لِّمَا يُرِيدُ","translations":{"bn":"তিনি যা চান, তাই করেন।","en":"Effecter of what He intends","id":"Mahakuasa berbuat apa yang Dia kehendaki","ru":"Он вершит то, что пожелает","tr":"Her dilediğini mutlaka yapandır","ur":"اور جو کچھ چاہے کر ڈالنے والا ہے"},"chapter":{"id":85,"name":"البروج","transliteration":"Al-Buruj","translations":{"bn":"নক্ষত্রপুঞ্জ","en":"The Mansions of the Stars","id":"Gugusan Bintang","ru":"Созвездия Зодиака","tr":"Burûc","ur":"برج"},"type":"meccan"}}
