{"id":6042,"number":19,"text":"وَٱلَّذِينَ كَفَرُواْ بِـَٔايَٰتِنَا هُمۡ أَصۡحَٰبُ ٱلۡمَشۡـَٔمَةِ","translations":{"bn":"আর যারা আমার আয়াতসমূহ অস্বীকার করে তারাই হতভাগা।","en":"But they who disbelieved in Our signs - those are the companions of the left","id":"Dan orang-orang yang kafir kepada ayat-ayat Kami, mereka itu adalah golongan kiri","ru":"Те же, которые не уверовали в Наши знамения, являются людьми левой стороны","tr":"Ayetlerimizi inkar edenler, işte onlar amel defterleri sollarından verilenlerdir","ur":"اور جنہوں نے ہماری آیات کو ماننے سے انکار کیا وہ بائیں بازو والے ہیں"},"chapter":{"id":90,"name":"البلد","transliteration":"Al-Balad","translations":{"bn":"নগর","en":"The City","id":"Negeri","ru":"Город","tr":"Beled","ur":"شہر"},"type":"meccan"}}
