{"id":868,"number":79,"text":"إِنِّي وَجَّهۡتُ وَجۡهِيَ لِلَّذِي فَطَرَ ٱلسَّمَٰوَٰتِ وَٱلۡأَرۡضَ حَنِيفٗاۖ وَمَآ أَنَا۠ مِنَ ٱلۡمُشۡرِكِينَ","translation":{"en":"Indeed, I have turned my face toward He who created the heavens and the earth, inclining toward truth, and I am not of those who associate others with Allah","id":"Aku hadapkan wajahku kepada (Allah) yang menciptakan langit dan bumi dengan penuh kepasrahan (mengikuti) agama yang benar, dan aku bukanlah termasuk orang-orang musyrik"},"chapter":{"id":6,"name":"الأنعام","transliteration":"Al-An'am","translation":{"en":"The Cattle","id":"Binatang Ternak"},"type":"meccan"}}
