{"id":972,"number":18,"text":"قَالَ ٱخۡرُجۡ مِنۡهَا مَذۡءُومٗا مَّدۡحُورٗاۖ لَّمَن تَبِعَكَ مِنۡهُمۡ لَأَمۡلَأَنَّ جَهَنَّمَ مِنكُمۡ أَجۡمَعِينَ","translations":{"en":"[Allah] said, \"Get out of Paradise, reproached and expelled. Whoever follows you among them - I will surely fill Hell with you, all together","es":"Dijo [Dios]: \"¡Sal de aquí degradado y despreciado! Llenaré el Infierno con todos aquellos que te sigan","fr":"«Sors de là», dit (Allah,) banni et rejeté. Quiconque te suit parmi eux... de vous tous, J'emplirai l'Enfer»","id":"(Allah) berfirman, \"Keluarlah kamu dari sana (surga) dalam keadaan terhina dan terusir! Sesungguhnya barang siapa di antara mereka ada yang mengikutimu, pasti akan Aku isi neraka Jahanam dengan kamu semua","ru":"Аллах сказал: «Изыди презренным и отверженным! А если кто из них последует за тобой, то Я заполню Геенну всеми вами","sv":"[Gud] sade: \"Ut härifrån, föraktad och utstött! Om någon sluter sig till dig skall Jag helt visst fylla helvetet med er alla","tr":"Allah, \"Yerilmiş ve kovulmuşsun, oradan defol; and olsun ki insanlardan sana kim uyarsa, hepinizi cehenneme dolduracağım\" dedi","ur":"فرمایا، \" نکل جا یہاں سے ذلیل اور ٹھکرایا ہوا یقین رکھ کہ اِن میں سے جو تیری پیروی کریں گے، تجھ سمیت ان سب سے جہنم کو بھر دوں گا","zh":"主说：“你被贬责地，被弃绝地从这里出去吧！他们中凡是顺从你的，我必以你和他们一起充满火狱。”"},"transliteration":"Qala okhruj minha mathooman madhooran laman tabiAAaka minhum laamlaanna jahannama minkum ajmaAAeena","chapter":{"id":7,"name":"الأعراف","transliteration":"Al-A'raf","translations":{"en":"The Heights","es":"Los Lugares Elevados","fr":"Al-A'raf","id":"Tempat-tempat Tinggi","ru":"Ограды","sv":"Urskiljning","tr":"A'râf","ur":"اونچی جگہ","zh":"高处"},"type":"meccan"}}
