{"number":1,"name":"ٱلْفَاتِحَةِ","transliteration":"Al-Faatiha","translation":"The Opening","revelation_type":"Meccan","total_verses":7,"verses":[{"number":1,"text":"En el Nombre de Dios, el Más Misericordioso, el Dispensador de Gracia"},{"number":2,"text":"Toda alabanza pertenece sólo a Dios, el Sustentador de todos los mundos,"},{"number":3,"text":"el Más Misericordioso, el Dispensador de Gracia,"},{"number":4,"text":"¡Señor del Día del Juicio!"},{"number":5,"text":"A Ti sólo adoramos; sólo en Ti buscamos ayuda."},{"number":6,"text":"¡Guíanos por el camino recto –"},{"number":7,"text":"el camino de aquellos sobre los que has derramado Tus bendiciones, no el de aquellos que han sido condenados [por Ti], ni el de aquellos que andan extraviados!"}]}
