{"number":114,"name":"النَّاسِ","transliteration":"An-Nas","translation":"Manusia","revelation_type":"Makkiyah","total_verses":6,"verses":[{"number":1,"text":"Katakanlah: \"Aku berlindung kepada Tuhan (yang memelihara dan menguasai) manusia."},{"number":2,"text":"Raja manusia."},{"number":3,"text":"Sembahan manusia."},{"number":4,"text":"Dari kejahatan (bisikan) syaitan yang biasa bersembunyi,"},{"number":5,"text":"yang membisikkan (kejahatan) ke dalam dada manusia,"},{"number":6,"text":"dari (golongan) jin dan manusia."}]}
