{"id":89,"name":"الفجر","transliteration":"Al-Fajr","translation":"La Aurora","type":"meccan","total_verses":30,"verses":[{"id":1,"text":"وَٱلۡفَجۡرِ","translation":"Juro por la Aurora","transliteration":"Waalfajri"},{"id":2,"text":"وَلَيَالٍ عَشۡرٖ","translation":"por las diez noches","transliteration":"Walayalin AAashrin"},{"id":3,"text":"وَٱلشَّفۡعِ وَٱلۡوَتۡرِ","translation":"por [las oraciones] pares e impares","transliteration":"WaalshshafAAi waalwatri"},{"id":4,"text":"وَٱلَّيۡلِ إِذَا يَسۡرِ","translation":"y por la noche cuando transcurre","transliteration":"Waallayli itha yasri"},{"id":5,"text":"هَلۡ فِي ذَٰلِكَ قَسَمٞ لِّذِي حِجۡرٍ","translation":"¿Acaso no son estos juramentos [argumentos suficientes sobre el poder de Dios] para los dotados de intelecto","transliteration":"Hal fee thalika qasamun lithee hijrin"},{"id":6,"text":"أَلَمۡ تَرَ كَيۡفَ فَعَلَ رَبُّكَ بِعَادٍ","translation":"¿No has visto cómo tu Señor castigó al pueblo de ‘Ád","transliteration":"Alam tara kayfa faAAala rabbuka biAAadin"},{"id":7,"text":"إِرَمَ ذَاتِ ٱلۡعِمَادِ","translation":"en Iram?, el de las [construcciones con grandes] columnas","transliteration":"Irama thati alAAimadi"},{"id":8,"text":"ٱلَّتِي لَمۡ يُخۡلَقۡ مِثۡلُهَا فِي ٱلۡبِلَٰدِ","translation":"que no tenía similar entre los otros pueblos [en su opulencia]","transliteration":"Allatee lam yukhlaq mithluha fee albiladi"},{"id":9,"text":"وَثَمُودَ ٱلَّذِينَ جَابُواْ ٱلصَّخۡرَ بِٱلۡوَادِ","translation":"Y al pueblo de Zamud, que esculpieron sus casas en las montañas rocosas del valle","transliteration":"Wathamooda allatheena jaboo alssakhra bialwadi"},{"id":10,"text":"وَفِرۡعَوۡنَ ذِي ٱلۡأَوۡتَادِ","translation":"Y al Faraón, el de las estacas","transliteration":"WafirAAawna thee alawtadi"},{"id":11,"text":"ٱلَّذِينَ طَغَوۡاْ فِي ٱلۡبِلَٰدِ","translation":"Todos ellos fueron tiranos con los pueblos","transliteration":"Allatheena taghaw fee albiladi"},{"id":12,"text":"فَأَكۡثَرُواْ فِيهَا ٱلۡفَسَادَ","translation":"sembrando la corrupción","transliteration":"Faaktharoo feeha alfasada"},{"id":13,"text":"فَصَبَّ عَلَيۡهِمۡ رَبُّكَ سَوۡطَ عَذَابٍ","translation":"Pero como consecuencia de eso tu Señor los azotó con un castigo","transliteration":"Fasabba AAalayhim rabbuka sawta AAathabin"},{"id":14,"text":"إِنَّ رَبَّكَ لَبِٱلۡمِرۡصَادِ","translation":"tu Señor está atento [a las acciones de la gente]","transliteration":"Inna rabbaka labialmirsadi"},{"id":15,"text":"فَأَمَّا ٱلۡإِنسَٰنُ إِذَا مَا ٱبۡتَلَىٰهُ رَبُّهُۥ فَأَكۡرَمَهُۥ وَنَعَّمَهُۥ فَيَقُولُ رَبِّيٓ أَكۡرَمَنِ","translation":"El ser humano, cuando su Señor lo agracia, dice: \"Mi Señor me ha honrado [porque lo merezco]","transliteration":"Faamma alinsanu itha ma ibtalahu rabbuhu faakramahu wanaAAAAamahu fayaqoolu rabbee akramani"},{"id":16,"text":"وَأَمَّآ إِذَا مَا ٱبۡتَلَىٰهُ فَقَدَرَ عَلَيۡهِ رِزۡقَهُۥ فَيَقُولُ رَبِّيٓ أَهَٰنَنِ","translation":"En cambio cuando lo pone a prueba restringiendo su sustento, dice: \"Mi Señor me ha despreciado [y no ha tenido en cuenta mis méritos]","transliteration":"Waamma itha ma ibtalahu faqadara AAalayhi rizqahu fayaqoolu rabbee ahanani"},{"id":17,"text":"كَلَّاۖ بَل لَّا تُكۡرِمُونَ ٱلۡيَتِيمَ","translation":"¡Pero no! No han comprendido el verdadero significado de las pruebas [de la riqueza y la pobreza] y por eso no son generosos con el huérfano","transliteration":"Kalla bal la tukrimoona alyateema"},{"id":18,"text":"وَلَا تَحَـٰٓضُّونَ عَلَىٰ طَعَامِ ٱلۡمِسۡكِينِ","translation":"ni exhortan unos a otros a alimentar al pobre","transliteration":"Wala tahaddoona AAala taAAami almiskeeni"},{"id":19,"text":"وَتَأۡكُلُونَ ٱلتُّرَاثَ أَكۡلٗا لَّمّٗا","translation":"[En lugar de eso] se apropian codiciosamente de los bienes del prójimo","transliteration":"Watakuloona altturatha aklan lamman"},{"id":20,"text":"وَتُحِبُّونَ ٱلۡمَالَ حُبّٗا جَمّٗا","translation":"y son insaciables en su amor [y codicia] por el dinero","transliteration":"Watuhibboona almala hubban jamman"},{"id":21,"text":"كَلَّآۖ إِذَا دُكَّتِ ٱلۡأَرۡضُ دَكّٗا دَكّٗا","translation":"¡Basta! [Piensen en cuál será su destino] cuando la Tierra sea golpeada una y otra vez","transliteration":"Kalla itha dukkati alardu dakkan dakkan"},{"id":22,"text":"وَجَآءَ رَبُّكَ وَٱلۡمَلَكُ صَفّٗا صَفّٗا","translation":"y llegue su Señor y se presenten los ángeles en fila tras fila","transliteration":"Wajaa rabbuka waalmalaku saffan saffan"},{"id":23,"text":"وَجِاْيٓءَ يَوۡمَئِذِۭ بِجَهَنَّمَۚ يَوۡمَئِذٖ يَتَذَكَّرُ ٱلۡإِنسَٰنُ وَأَنَّىٰ لَهُ ٱلذِّكۡرَىٰ","translation":"y sea traído el Infierno. Ese día el hombre recordará sus obras, pero de nada le servirá","transliteration":"Wajeea yawmaithin bijahannama yawmaithin yatathakkaru alinsanu waanna lahu alththikra"},{"id":24,"text":"يَقُولُ يَٰلَيۡتَنِي قَدَّمۡتُ لِحَيَاتِي","translation":"Y dirá lamentándose: \"¡Ojalá hubiera realizado buenas obras para mi vida [del más allá]","transliteration":"Yaqoolu ya laytanee qaddamtu lihayatee"},{"id":25,"text":"فَيَوۡمَئِذٖ لَّا يُعَذِّبُ عَذَابَهُۥٓ أَحَدٞ","translation":"Sepan que nadie ha castigado como Él castigará ese día","transliteration":"Fayawmaithin la yuAAaththibu AAathabahu ahadun"},{"id":26,"text":"وَلَا يُوثِقُ وَثَاقَهُۥٓ أَحَدٞ","translation":"y nadie ha encadenado como Él encadenará [ese día]","transliteration":"Wala yoothiqu wathaqahu ahadun"},{"id":27,"text":"يَـٰٓأَيَّتُهَا ٱلنَّفۡسُ ٱلۡمُطۡمَئِنَّةُ","translation":"[Le será dicho al creyente:] \"¡Oh, alma que estás en paz con tu Señor","transliteration":"Ya ayyatuha alnnafsu almutmainnatu"},{"id":28,"text":"ٱرۡجِعِيٓ إِلَىٰ رَبِّكِ رَاضِيَةٗ مَّرۡضِيَّةٗ","translation":"Vuelve a la vera de tu Señor complacida, porque Dios está complacido contigo","transliteration":"IrjiAAee ila rabbiki radiyatan mardiyyatan"},{"id":29,"text":"فَٱدۡخُلِي فِي عِبَٰدِي","translation":"y únete a Mis siervos piadosos","transliteration":"Faodkhulee fee AAibadee"},{"id":30,"text":"وَٱدۡخُلِي جَنَّتِي","translation":"entrando a Mi Paraíso","transliteration":"Waodkhulee jannatee"}]}
